MANIFEST.in
requirements.txt
setup.cfg
setup.py
dervish/__init__.py
dervish/dervish.py
dervish/index.py
dervish/log.py
dervish/store.py
dervish/whirling.py
dervish.egg-info/PKG-INFO
dervish.egg-info/SOURCES.txt
dervish.egg-info/dependency_links.txt
dervish.egg-info/entry_points.txt
dervish.egg-info/requires.txt
dervish.egg-info/top_level.txt