Metadata-Version: 1.0
Name: dervish
Version: 0.0.11
Summary: Demonstrates AWS kinesis consumers writing events to s3 and indexing them in dynamodb.
Home-page: http://packages.python.org/dervish
Author: Luke Samaha
Author-email: lwsamaha@gmail.com
License: BSD
Keywords: aws kinesis consumer dynamodb event
Platform: UNKNOWN
